worky/__init__.py
worky/__main__.py
worky/assets/completion/worky.bash
worky/main.py
worky/models/__init__.py
worky/models/config_model.py
worky/models/log_level.py
worky/utils/__init__.py
worky/utils/logger.py
worky/utils/util.py
worky-1.0.4.dist-info/LICENSE
worky-1.0.4.dist-info/METADATA
worky-1.0.4.dist-info/WHEEL
worky-1.0.4.dist-info/entry_points.txt
worky-1.0.4.dist-info/RECORD
