Metadata-Version: 2.1
Name: worky
Version: 1.0.4
Summary: Worky is a tool that helps to define and load project workspaces.
Home-page: https://github.com/ZappaBoy/worky
Keywords: worky,productivity,workspace,initializer
Author: ZappaBoy
Author-email: federico.zappone@justanother.cloud
Maintainer: ZappaBoy
Maintainer-email: federico.zappone@justanother.cloud
Requires-Python: >=3.10,<4.0
Classifier: Programming Language :: Python :: 3
Classifier: Programming Language :: Python :: 3.10
Classifier: Programming Language :: Python :: 3.11
Classifier: Programming Language :: Python :: 3.12
Classifier: Topic :: Utilities
Requires-Dist: toml (>=0.10.2,<0.11.0)
Project-URL: Documentation, https://github.com/ZappaBoy/worky/blob/main/README.md
Project-URL: Repository, https://github.com/ZappaBoy/worky
